BingGPT.py
revBingGPT-0.0.1.dist-info/METADATA
revBingGPT-0.0.1.dist-info/WHEEL
revBingGPT-0.0.1.dist-info/top_level.txt
revBingGPT-0.0.1.dist-info/RECORD
