Metadata-Version: 2.1
Name: revBingGPT
Version: 0.0.1
Summary: Reverse engineered Bing Chat API
Home-page: https://github.com/acheong08/BingGPT
Author: Antonio Cheong
Author-email: acheong@student.dalat.org
License: GNU General Public License v2.0
Requires-Dist: asyncio
Requires-Dist: requests
Requires-Dist: websockets
